{"doc":{"isMarkdown":true,"isTranslated":false,"isActive":true,"flaws":{},"title":"Compile time","mdn_url":"/en-US/docs/Glossary/Compile_time","locale":"en-US","native":"English (US)","sidebarHTML":"","body":[{"type":"prose","value":{"id":null,"title":null,"isH3":false,"content":"<p>The <em>compile time</em> is the time from when the program is first loaded until the program is <a href=\"/en-US/docs/Glossary/Parse\">parsed</a>.</p>"}},{"type":"prose","value":{"id":"see_also","title":"See also","isH3":false,"content":"<ul>\n  <li><a href=\"https://en.wikipedia.org/wiki/Compile_time\" class=\"external\" rel=\" noopener\">Compile time</a> on Wikipedia</li>\n</ul>"}}],"toc":[{"text":"See also","id":"see_also"}],"summary":"The compile time is the time from when the program is first loaded until the program is parsed.","popularity":0,"modified":"2022-09-21T02:09:26.000Z","other_translations":[{"title":"Tiempo de compilación","locale":"es","native":"Español"},{"title":"Moment de compilation","locale":"fr","native":"Français"},{"title":"Compile time (コンパイル時間)","locale":"ja","native":"日本語"},{"title":"编译时间","locale":"zh-CN","native":"中文 (简体)"},{"title":"編譯時間","locale":"zh-TW","native":"正體中文 (繁體)"}],"source":{"folder":"en-us/glossary/compile_time","github_url":"https://github.com/mdn/content/blob/style/old/files/en-us/glossary/compile_time/index.md","last_commit_url":"https://github.com/mdn/content/commit/ed947b2c608428b62a60f07d09dc543f732dc09b","filename":"index.md"},"parents":[{"uri":"/en-US/docs/Glossary","title":"MDN Web Docs Glossary: Definitions of Web-related terms"},{"uri":"/en-US/docs/Glossary/Compile_time","title":"Compile time"}],"pageTitle":"Compile time - MDN Web Docs Glossary: Definitions of Web-related terms | MDN","noIndexing":false}}