{"doc":{"isMarkdown":true,"isTranslated":false,"isActive":true,"flaws":{},"title":"WebSocket.extensions","mdn_url":"/en-US/docs/Web/API/WebSocket/extensions","locale":"en-US","native":"English (US)","sidebarHTML":"<ol><li><strong><a href=\"/en-US/docs/Web/API/WebSocket\"><code>WebSocket</code></a></strong></li><li class=\"toggle\"><details open=\"\"><summary>Constructor</summary><ol><li><a href=\"/en-US/docs/Web/API/WebSocket/WebSocket\"><code>WebSocket()</code></a></li></ol></details></li><li class=\"toggle\"><details open=\"\"><summary>Properties</summary><ol><li><a href=\"/en-US/docs/Web/API/WebSocket/binaryType\"><code>binaryType</code></a></li><li><a href=\"/en-US/docs/Web/API/WebSocket/bufferedAmount\"><code>bufferedAmount</code></a></li><li><em><code>extensions</code></em></li><li><a href=\"/en-US/docs/Web/API/WebSocket/protocol\"><code>protocol</code></a></li><li><a href=\"/en-US/docs/Web/API/WebSocket/readyState\"><code>readyState</code></a></li><li><a href=\"/en-US/docs/Web/API/WebSocket/url\"><code>url</code></a></li></ol></details></li><li class=\"toggle\"><details open=\"\"><summary>Methods</summary><ol><li><a href=\"/en-US/docs/Web/API/WebSocket/close\"><code>close()</code></a></li><li><a href=\"/en-US/docs/Web/API/WebSocket/send\"><code>send()</code></a></li></ol></details></li><li class=\"toggle\"><details open=\"\"><summary>Events</summary><ol><li><a href=\"/en-US/docs/Web/API/WebSocket/close_event\"><code>close</code></a></li><li><a href=\"/en-US/docs/Web/API/WebSocket/error_event\"><code>error</code></a></li><li><a href=\"/en-US/docs/Web/API/WebSocket/message_event\"><code>message</code></a></li><li><a href=\"/en-US/docs/Web/API/WebSocket/open_event\"><code>open</code></a></li></ol></details></li><li class=\"toggle\"><details open=\"\"><summary>Inheritance:</summary><ol><li><a href=\"/en-US/docs/Web/API/EventTarget\"><code>EventTarget</code></a></li></ol></details></li></ol>","body":[{"type":"prose","value":{"id":null,"title":null,"isH3":false,"content":"<p>\n  The <strong><code>WebSocket.extensions</code></strong> read-only property returns the\n  extensions selected by the server. This is currently only the empty string or a list of\n  extensions as negotiated by the connection.\n</p>"}},{"type":"prose","value":{"id":"value","title":"Value","isH3":false,"content":"<p>A string.</p>"}},{"type":"specifications","value":{"title":"Specifications","id":"specifications","isH3":false,"specifications":[{"bcdSpecificationURL":"https://html.spec.whatwg.org/multipage/web-sockets.html#dom-websocket-extensions-dev","title":"HTML Standard"}],"query":"api.WebSocket.extensions"}},{"type":"browser_compatibility","value":{"title":"Browser compatibility","id":"browser_compatibility","isH3":false,"query":"api.WebSocket.extensions","dataURL":"/en-US/docs/Web/API/WebSocket/extensions/bcd.json"}}],"toc":[{"text":"Value","id":"value"},{"text":"Specifications","id":"specifications"},{"text":"Browser compatibility","id":"browser_compatibility"}],"summary":"The WebSocket.extensions read-only property returns the\n  extensions selected by the server. This is currently only the empty string or a list of\n  extensions as negotiated by the connection.","popularity":0.0005,"modified":"2022-09-09T05:19:45.000Z","other_translations":[{"title":"WebSocket.extensions","locale":"fr","native":"Français"},{"title":"WebSocket.extensions","locale":"ja","native":"日本語"},{"title":"WebSocket.extensions","locale":"zh-CN","native":"中文 (简体)"}],"source":{"folder":"en-us/web/api/websocket/extensions","github_url":"https://github.com/mdn/content/blob/style/old/files/en-us/web/api/websocket/extensions/index.md","last_commit_url":"https://github.com/mdn/content/commit/f7dae62645a2c735ed6f6ed63f664bf279fdfc4b","filename":"index.md"},"parents":[{"uri":"/en-US/docs/Web","title":"Web technology for developers"},{"uri":"/en-US/docs/Web/API","title":"Web APIs"},{"uri":"/en-US/docs/Web/API/WebSocket","title":"WebSocket"},{"uri":"/en-US/docs/Web/API/WebSocket/extensions","title":"WebSocket.extensions"}],"pageTitle":"WebSocket.extensions - Web APIs | MDN","noIndexing":false}}