{"doc":{"isMarkdown":true,"isTranslated":true,"isActive":true,"flaws":{},"title":"Control flow (制御フロー)","mdn_url":"/ja/docs/Glossary/Control_flow","locale":"ja","native":"日本語","sidebarHTML":"","body":[{"type":"prose","value":{"id":null,"title":null,"isH3":false,"content":"<p><em>制御フロー</em>（制御の流れ）は、コンピューターがスクリプト内の文を実行する順序です。</p>\n<p>条件やループなどの（非常によく出てくる）制御フローを変更する構造にコンピューターが出合わない限り、コードはファイルの最初の行から順に最後の行まで実行します。</p>\n<p>たとえば、ウェブページのフォームからのユーザーのデータを検証するために使用されるスクリプトを想像してみてください。 スクリプトは有効なデータを送信しますが、ユーザーが必要なフィールドを空のままにしておくと、スクリプトはそれを入力するように要求します。 これを行うには、スクリプトは<a href=\"/ja/docs/Glossary/Conditional\">条件付き</a>構造または <code>if...else</code> を使用し、フォームが完全であるかどうかによって異なるコードを実行します。</p>\n<pre class=\"notranslate\">if (field==empty) {\n    promptUser();\n} else {\n    submitForm();\n}\n</pre>\n<p><a href=\"/ja/docs/Glossary/JavaScript\">JavaScript</a> や <a href=\"/ja/docs/Glossary/PHP\">PHP</a> などの一般的なスクリプトには、条件付き、<a href=\"/ja/docs/Glossary/loop\">ループ</a>、<a href=\"/ja/docs/Glossary/Function\">関数</a>などの多くの制御構造が含まれています。 スクリプトの一部は、<a href=\"/ja/docs/Glossary/event\">イベント</a>が発生したときに実行するように設定することもできます。</p>\n<p>たとえば、上記の抜粋は、ユーザーがフォームの [送信] ボタンをクリックしたときに実行される関数内にある可能性があります。 この関数にはループを含めることもできます。 ループは、フォーム内のすべてのフィールドを反復し、それぞれを順にチェックします。 <code>if</code> と <code>else</code> のセクションのコードを振り返ってみると、<code>promptUser</code> と <code>submitForm</code> という行はスクリプト内の他の関数を呼び出すこともできます。 ご覧のように、制御構造はわずか数行のコードでも複雑な処理フローを指示することがあります。</p>\n<p>制御フローとは、スクリプトを読むときに、最初から最後まで読むだけでなく、プログラムの構造や実行順序にどのように影響するかを調べる必要があることを意味します。</p>"}},{"type":"prose","value":{"id":"より詳しく知る","title":"より詳しく知る","isH3":false,"content":""}},{"type":"prose","value":{"id":"一般知識","title":"一般知識","isH3":true,"content":"<ul>\n  <li>Wikipedia 上の <a title=\"制御構造\" href=\"https://ja.wikipedia.org/wiki/制御構造\" class=\"external\" rel=\" noopener\">制御構造</a></li>\n</ul>"}},{"type":"prose","value":{"id":"技術文書","title":"技術文書","isH3":true,"content":"<ul>\n  <li>MDN の <a href=\"/ja/docs/Web/JavaScript/Reference#control_flow\">JavaScript リファレンス - 制御フロー</a></li>\n</ul>"}},{"type":"prose","value":{"id":"それについて学ぶ","title":"それについて学ぶ","isH3":true,"content":"<ul>\n  <li>MDN の <a href=\"/ja/docs/Web/JavaScript/Guide/Control_flow_and_error_handling\">文（制御フロー）</a></li>\n</ul>"}}],"toc":[{"text":"より詳しく知る","id":"より詳しく知る"}],"summary":"制御フロー（制御の流れ）は、コンピューターがスクリプト内の文を実行する順序です。","popularity":0,"modified":"2022-10-01T03:41:16.000Z","other_translations":[{"title":"Control flow","locale":"en-US","native":"English (US)"},{"title":"Structure de contrôle","locale":"fr","native":"Français"},{"title":"控制流","locale":"zh-CN","native":"中文 (简体)"}],"source":{"folder":"ja/glossary/control_flow","github_url":"https://github.com/mdn/translated-content/blob/main/files/ja/glossary/control_flow/index.md","last_commit_url":"https://github.com/mdn/translated-content/commit/921c46a374ab0a9f4cc809af0370f8c412e54701","filename":"index.md"},"parents":[{"uri":"/ja/docs/Glossary","title":"MDN Web Docs 用語集: ウェブ関連用語の定義"},{"uri":"/ja/docs/Glossary/Control_flow","title":"Control flow (制御フロー)"}],"pageTitle":"Control flow (制御フロー) - MDN Web Docs 用語集: ウェブ関連用語の定義 | MDN","noIndexing":false}}